text_analyzer/__init__.py
text_analyzer/analyzer.py
text_analyzer_v1-1.0.0.dist-info/licenses/LICENSE
text_analyzer_v1-1.0.0.dist-info/METADATA
text_analyzer_v1-1.0.0.dist-info/WHEEL
text_analyzer_v1-1.0.0.dist-info/top_level.txt
text_analyzer_v1-1.0.0.dist-info/RECORD
