Metadata-Version: 2.4
Name: text-analyzer-v1
Version: 1.0.0
Summary: A simple Python package for analyzing text statistics
Author-email: Sarif Mia <sarifmia.ofc@gmail.com>
License: MIT
Project-URL: Homepage, https://github.com/yourusername/text-analyzer
Project-URL: Repository, https://github.com/yourusername/text-analyzer
Project-URL: Issues, https://github.com/yourusername/text-analyzer/issues
Classifier: Development Status :: 3 - Alpha
Classifier: Intended Audience :: Developers
Classifier: License :: OSI Approved :: MIT License
Classifier: Programming Language :: Python :: 3
Classifier: Programming Language :: Python :: 3.6
Classifier: Programming Language :: Python :: 3.7
Classifier: Programming Language :: Python :: 3.8
Classifier: Programming Language :: Python :: 3.9
Classifier: Programming Language :: Python :: 3.10
Classifier: Programming Language :: Python :: 3.11
Requires-Python: >=3.6
License-File: LICENSE
Dynamic: license-file
